soketdb/__init__.py
soketdb-1.4.2.dist-info/licenses/LICENSE
soketdb-1.4.2.dist-info/METADATA
soketdb-1.4.2.dist-info/WHEEL
soketdb-1.4.2.dist-info/top_level.txt
soketdb-1.4.2.dist-info/RECORD
