Metadata-Version: 2.4
Name: soketdb
Version: 1.4.2
Summary: SoketDB — a zero-setup, AI-smart JSON database built for developers who value speed, simplicity, and offline capability.
Home-page: https://github.com/pythos-team/soketdb
Author: Alex Austin
Author-email: Alex Austin <benmap40@gmail.com>
License: MIT
Project-URL: Homepage, https://github.com/pythos-team/soketdb
Project-URL: Bug Tracker, https://github.com/pythos-team/soketdb/issues
Keywords: database,json,sql,ai,offline,lightweight,huggingface,google-drive,cloud-sync
Classifier: Development Status :: 5 - Production/Stable
Classifier: Intended Audience :: Developers
Classifier: License :: OSI Approved :: MIT License
Classifier: Programming Language :: Python :: 3
Classifier: Programming Language :: Python :: 3.8
Classifier: Operating System :: OS Independent
Classifier: Topic :: Database
Classifier: Topic :: Software Development :: Libraries :: Python Modules
Requires-Python: >=3.7
License-File: LICENSE
Requires-Dist: huggingface_hub
Requires-Dist: sqlparse
Requires-Dist: requests
Requires-Dist: redis
Requires-Dist: dropbox
Requires-Dist: boto3
Requires-Dist: google-auth-oauthlib
Requires-Dist: google-auth-httplib2
Dynamic: author
Dynamic: home-page
Dynamic: license-file
Dynamic: requires-python
